config_renderer/__init__.py
config_renderer/__main__.py
config_renderer-1.0.2.dist-info/LICENSE
config_renderer-1.0.2.dist-info/METADATA
config_renderer-1.0.2.dist-info/WHEEL
config_renderer-1.0.2.dist-info/entry_points.txt
config_renderer-1.0.2.dist-info/top_level.txt
config_renderer-1.0.2.dist-info/RECORD
